file_processor_sdk/__init__.py
file_processor_sdk/process_doc.py
file_processor_sdk/process_docx.py
file_processor_sdk/process_file.py
file_processor_sdk/process_pdf.py
file_processor_sdk/process_txt.py
file_processor_sdk/save_to_txt.py
file_processor_sdk-0.1.0.dist-info/METADATA
file_processor_sdk-0.1.0.dist-info/WHEEL
file_processor_sdk-0.1.0.dist-info/entry_points.txt
file_processor_sdk-0.1.0.dist-info/top_level.txt
file_processor_sdk-0.1.0.dist-info/RECORD
