Metadata-Version: 2.1
Name: file_processor_sdk
Version: 0.1.0
Classifier: Development Status :: 3 - Alpha
Classifier: Intended Audience :: Developers
Classifier: Programming Language :: Python :: 3
Classifier: Programming Language :: Python :: 3.6
Classifier: Programming Language :: Python :: 3.7
Classifier: Programming Language :: Python :: 3.8
Classifier: Programming Language :: Python :: 3.9
Requires-Dist: python-docx
Requires-Dist: PyPDF2
Requires-Dist: pywin32
